easydes/__init__.py
easydes/deslib.py
easydes-0.2.1.dist-info/LICENSE
easydes-0.2.1.dist-info/METADATA
easydes-0.2.1.dist-info/WHEEL
easydes-0.2.1.dist-info/top_level.txt
easydes-0.2.1.dist-info/RECORD
