Metadata-Version: 2.1
Name: easydes
Version: 0.2.1
Summary: DES encryption wrapper package
Author-email: easydes <desperateufo@icloud.com>
Project-URL: Homepage, https://github.com/pypa/sampleproject
Project-URL: Bug Tracker, https://github.com/pypa/sampleproject/issues
Classifier: Programming Language :: Python :: 3
Classifier: License :: OSI Approved :: MIT License
Classifier: Operating System :: OS Independent
Requires-Python: >=3.7
License-File: LICENSE
